{
  "development": {
    "ATTRS": {
      "name": "DEVELOPMENT"
    },
    "JIRA": {
      "TICKETS": {
        "FEEDBACK": "UGNE-1417"
      }
    },
    "ENDPOINTS": {
      "API": "http://10.9.202.110:8001/api/1.0",
      "VARDB": "http://vardbweb01.bcgsc.ca:6543",
      "SOCKET": "http://localhost:8002"
    },
    "CONNECT": {
      "PORT": 3000,
      "CREATE": true,
      "LIVE_RELOAD": true
    }
  },
  "production": {
    "ATTRS": {
      "name": "PRODUCTION"
    },
    "JIRA": {
      "TICKETS": {
        "FEEDBACK": "UGNE-1414"
      }
    },
    "ENDPOINTS": {
      "API": "http://iprweb01.bcgsc.ca:8001/api/1.0",
      "VARDB": "http://vardbweb01.bcgsc.ca",
      "SOCKET": "http://iprweb01.bcgsc.ca:8002"
    },
    "CONNECT": {
      "PORT": 8000,
      "CREATE": true,
      "LIVE_RELOAD": false
    }
  }
}